calc9000/__init__.py
calc9000/converse.py
calc9000/datatypes.py
calc9000/forge.py
calc9000/functions.py
calc9000/larker.py
calc9000/main.py
calc9000/references.py
calc9000-0.dist-info/LICENSE
calc9000-0.dist-info/METADATA
calc9000-0.dist-info/WHEEL
calc9000-0.dist-info/top_level.txt
calc9000-0.dist-info/RECORD
