Metadata-Version: 2.1
Name: calc9000
Version: 0
Summary: UNKNOWN
Home-page: https://github.com/weakit/calc9000
Author: weakit
License: UNKNOWN
Platform: UNKNOWN
Requires-Python: >=3.6
Requires-Dist: sympy (>=1.4)
Requires-Dist: lark-parser
